{
    "id": 85455000,
    "name": "Zodiac 4 Unnerfed",
    "author": "PanPingwinek",
    "creators": ["PanPingwinek"],
    "verifier": "Cinasek",
    "verification": "https://youtu.be/P_uJEeN-uLo?si=RmXHrL7owSvit-nZ&t=198",
    "percentToQualify": 100,
    "password": "None",
    "enjoyment": "8/10",
    "description": "Bianox's Zodiac part in it's prime",
    "records": [
        {
            "user": "gopsolaptop",
            "link": "https://youtu.be/DG2pgIg163c?t=51",
            "percent": 100,
            "hz": 240
        },
        {
            "user": "qnet309",
            "link": "https://medal.tv/games/geometry-dash/clips/n3c87pI643hJFSeLp?invite=cr-MSxqZ2osNDU1NzMyNDU3",
            "percent": 100,
            "hz": 240
        },
        {
            "user": "Specie",
            "link": "https://youtu.be/VhlKLhRlxM0",
            "percent": 100,
            "hz": 240
        }
    ]
}
